{"washerwoman":["washerwoman","librarian","grandmother","investigator"],"washerwoman_townsfolk":["washerwoman_townsfolk","librarian_outsider","grandmother_grandchild"],"washerwoman_wrong":["washerwoman_wrong","librarian_wrong","investigator_wrong","grandmother_dead","eviltwin_twin"],"librarian":["librarian","washerwoman","balloonist","investigator","grandmother"],"librarian_outsider":["librarian_outsider","washerwoman_townsfolk","grandmother_grandchild","sailor_drunk","eviltwin_twin"],"librarian_wrong":["librarian_wrong","washerwoman_wrong","investigator_wrong","grandmother_dead","eviltwin_twin"],"investigator":["investigator","towncrier","librarian","washerwoman","grandmother"],"investigator_minion":["investigator_minion","towncrier_minionnominated","librarian_townsfolk","washerwoman_townsfolk","grandmother_grandchild"],"investigator_wrong":["investigator_wrong","towncrier_minionnotnominated","librarian_wrong","washerwoman_wrong","grandmother_dead"],"chef":["chef","clockmaker","investigator","grandmother"],"empath":["empath","tealady","clockmaker","oracle","villageidiot"],"fortuneteller":["fortuneteller","bountyhunter","chambermaid","flowergirl",""],"fortuneteller_redherring":["fortuneteller_redherring","librarian_outsider","mathematician_abnormal","goon_drunk"],"undertaker":["undertaker","cannibal","gambler","ravenkeeper","oracle"],"undertaker_executed":["undertaker_executed","cannibal_lunch","gambler_dead"],"monk":["monk","innkeeper","tealady","lycanthrope"],"monk_protected":["monk_protected","innkeeper_protected","tealady_cannotdie"],"ravenkeeper":["ravenkeeper","sage","banshee","pacifist","fool","moonchild","klutz"],"virgin":["virgin","towncrier","mutant"],"virgin_noability":["virgin_noability","seamstress_noability","artist_noability"],"slayer":["slayer","exorcist","courtier","alsaahir","psychopath"],"slayer_noability":["slayer_noability","seamstress_noability","artist_noability"],"soldier":["soldier","fool","sage","banshee","innkeeper","professor"],"mayor":["mayor","cult_leader"],"butler":["butler","ogre","zealot","klutz","moonchild"],"drunk":["drunk","lunatic","marionette","sweetheart","tinker"],"recluse":["recluse","cultleader","mutant"],"saint":["saint","klutz","moonchild","heretic","damsel"],"poisoner":["poisoner","cerenovus","snake_charmer","sailor",""],"spy":["spy","widow","boffin","mastermind"],"scarletwoman":["scarletwoman","mastermind","summoner"],"baron":["baron","godfather","xaan","boffin","evil_twin"],"imp":["imp","fanggu","po","vigor_mortis","riot"],"philosopher":["philosopher","professor","virgin","saint","goon"],"snakecharmer":["snakecharmer","fortuneteller","sage","exorcist"],"towncrier":["towncrier","undertaker","virgin"],"noble":["noble","investigator","juggler","clockmaker"],"noble_seen":["noble_seen","investigator_wrong","investigator_minion","librarian_outsider","librarian_wrong","juggler_correct"],"pixie":["pixie","washerwoman","librarian","mutant"],"pixie_mad":["pixie_mad","cerenovus_mad","harpy_mad","butler_master","eviltwin_twin"],"bountyhunter":["bountyhunter","investigator","towncrier","seamstress","fortuneteller","soldier"],"highpriestess":["highpriestess","monk","librarian","grandmother","courtier"],"preacher":["preacher","exorcist","sailor","innkeeper"],"villageidiot":["villageidiot","imp","farmer","fool","sailor","savant"],"cannibal":["cannibal","undertaker","minstrel"],"hatter":["hatter","barber","goon","butler"],"puzzlemaster":["puzzlemaster","sweetheart","moonchild","mathematician"],"widow":["widow","spy","mastermind","witch","boffin"],"ojo":["ojo","po","pukka"],"legion":["legion","fanggu","po","shabaloth","vigormortis","nodashii","zombuul","pukka","imp","recluse"]}
